emphases/__init__.py
emphases/__main__.py
emphases/convert.py
emphases/core.py
emphases/load.py
emphases/annotate/__init__.py
emphases/annotate/__main__.py
emphases/annotate/core.py
emphases/assets/checkpoints/checkpoint.pt
emphases/assets/configs/annotate.yaml
emphases/assets/partitions/automatic.json
emphases/assets/partitions/buckeye.json
emphases/assets/partitions/crowdsource.json
emphases/assets/partitions/libritts.json
emphases/baselines/__init__.py
emphases/baselines/duration_variance/__init__.py
emphases/baselines/duration_variance/core.py
emphases/baselines/pitch_variance/__init__.py
emphases/baselines/pitch_variance/core.py
emphases/baselines/prominence/__init__.py
emphases/baselines/prominence/core.py
emphases/baselines/prominence/cwt_utils.py
emphases/baselines/prominence/duration_processing.py
emphases/baselines/prominence/energy_processing.py
emphases/baselines/prominence/f0_processing.py
emphases/baselines/prominence/filter.py
emphases/baselines/prominence/loma.py
emphases/baselines/prominence/pitch_tracker.py
emphases/baselines/prominence/smooth_and_interp.py
emphases/config/__init__.py
emphases/config/defaults.py
emphases/config/static.py
emphases/data/__init__.py
emphases/data/collate.py
emphases/data/dataset.py
emphases/data/loader.py
emphases/data/sampler.py
emphases/data/download/__init__.py
emphases/data/download/__main__.py
emphases/data/download/core.py
emphases/data/preprocess/__init__.py
emphases/data/preprocess/__main__.py
emphases/data/preprocess/core.py
emphases/data/preprocess/loudness.py
emphases/data/preprocess/mels.py
emphases/evaluate/__init__.py
emphases/evaluate/__main__.py
emphases/evaluate/core.py
emphases/evaluate/metrics.py
emphases/model/__init__.py
emphases/model/core.py
emphases/model/layers/__init__.py
emphases/model/layers/convolution.py
emphases/model/layers/transformer.py
emphases/partition/__init__.py
emphases/partition/__main__.py
emphases/partition/core.py
emphases/plot/__init__.py
emphases/plot/core.py
emphases-0.0.2.dist-info/LICENSE
emphases-0.0.2.dist-info/METADATA
emphases-0.0.2.dist-info/WHEEL
emphases-0.0.2.dist-info/top_level.txt
emphases-0.0.2.dist-info/RECORD
