Metadata-Version: 2.1
Name: emphases
Version: 0.0.2
Summary: Crowdsourced and Automatic Speech Prominence Estimation
Home-page: https://github.com/interactiveaudiolab/emphases
Author: Interactive Audio Lab
Author-email: interactiveaudiolab@gmail.com
License: MIT
Keywords: annotatation,audio,emphasis,prominence,speech
Classifier: License :: OSI Approved :: MIT License
License-File: LICENSE
Requires-Dist: GPUtil
Requires-Dist: huggingface-hub
Requires-Dist: librosa
Requires-Dist: matplotlib
Requires-Dist: numpy
Requires-Dist: penn
Requires-Dist: pycwt
Requires-Dist: pyfoal
Requires-Dist: pypar
Requires-Dist: pyyaml
Requires-Dist: reseval
Requires-Dist: scipy
Requires-Dist: torch
Requires-Dist: torchutil
Requires-Dist: torchaudio
Requires-Dist: yapecs
